montagu_deploy/__about__.py
montagu_deploy/__init__.py
montagu_deploy/cli.py
montagu_deploy/config.py
montagu_deploy/database.py
montagu_deploy/montagu_constellation.py
montagu_deploy-0.1.3.dist-info/METADATA
montagu_deploy-0.1.3.dist-info/WHEEL
montagu_deploy-0.1.3.dist-info/entry_points.txt
montagu_deploy-0.1.3.dist-info/licenses/LICENSE.txt
montagu_deploy-0.1.3.dist-info/RECORD
