Metadata-Version: 2.4
Name: montagu-deploy
Version: 0.1.3
Summary: Deploy tool for the Montagu web app
Project-URL: Documentation, https://github.com/vimc/montagu-deploy#readme
Project-URL: Issues, https://github.com/vimc/montagu-deploy/issues
Project-URL: Source, https://github.com/vimc/montagu-deploy
Author-email: Alex <alex.hill@gmail.com>
License-Expression: MIT
License-File: LICENSE.txt
Classifier: Development Status :: 4 - Beta
Classifier: Programming Language :: Python
Classifier: Programming Language :: Python :: 3.10
Classifier: Programming Language :: Python :: 3.11
Classifier: Programming Language :: Python :: 3.12
Classifier: Programming Language :: Python :: 3.13
Classifier: Programming Language :: Python :: Implementation :: CPython
Classifier: Programming Language :: Python :: Implementation :: PyPy
Requires-Python: >=3.10
Requires-Dist: constellation>=1.5.0
Requires-Dist: docopt
Requires-Dist: psycopg2
